marketing_analytics/__init__.py
marketing_analytics/core/__init__.py
marketing_analytics/core/base.py
marketing_analytics/core/config.py
marketing_analytics/core/exceptions.py
marketing_analytics/models/__init__.py
marketing_analytics/models/channel_attribution.py
marketing_analytics/models/customer_lifecycle.py
marketing_analytics/models/optimization.py
marketing_analytics/models/pricing.py
marketing_analytics/models/segmentation.py
marketing_analytics/utils/__init__.py
marketing_analytics/utils/metrics.py
marketing_analytics/utils/preprocessing.py
marketing_analytics/utils/validation.py
marketing_analytics/visualization/__init__.py
marketing_analytics/visualization/plots.py
marketing_analytics_toolkit-0.1.3.dist-info/LICENSE
marketing_analytics_toolkit-0.1.3.dist-info/METADATA
marketing_analytics_toolkit-0.1.3.dist-info/WHEEL
marketing_analytics_toolkit-0.1.3.dist-info/top_level.txt
marketing_analytics_toolkit-0.1.3.dist-info/RECORD
